{
  "schema": "npa-ai-proof-replay-v0.1",
  "module": "Proofs.Ai.Modularity.Semistable",
  "trusted": false,
  "profile": "explicit_term_source_certificate_handoff",
  "steps": [
    {
      "declaration": "SemistableModularityData",
      "source_kind": "explicit_def_value",
      "term": "fun GaloisRepresentation => fun DeformationFunctor => fun DeformationRing => fun HeckeAlgebra => fun DeformationRepresents => fun HeckeDeformationComparison => fun R_eq_T => fun ResidualIrreducible => fun LocalCondition => fun MinimalCondition => fun NonMinimalCondition => fun ModularityAssumption => fun ModularityConclusion => fun DeepAssumption => fun NonFreyUseCase => fun UsefulOutsideFrey => fun lifting_data => fun EllipticCurvePackage => fun LocalField => fun SemistableAt => fun GaloisRepresentationOfCurve => fun ReusableAssumptions => fun SemistableModularityConclusion => fun SemistableModularityRoute => fun NoBridgeAxiomDependency => forall (Q : Prop), forall (mk : forall (lifting_out : @ModularityLiftingData GaloisRepresentation DeformationFunctor DeformationRing HeckeAlgebra DeformationRepresents HeckeDeformationComparison R_eq_T ResidualIrreducible LocalCondition MinimalCondition NonMinimalCondition ModularityAssumption ModularityConclusion DeepAssumption NonFreyUseCase UsefulOutsideFrey), forall (semistable_assumptions_law : forall (curve : EllipticCurvePackage), forall (local_field : LocalField), SemistableAt curve local_field -> ReusableAssumptions curve), forall (semistable_conclusion_law : forall (curve : EllipticCurvePackage), forall (rho : GaloisRepresentation), GaloisRepresentationOfCurve curve rho -> ModularityConclusion rho -> SemistableModularityConclusion curve), forall (semistable_modularity_law : forall (curve : EllipticCurvePackage), forall (local_field : LocalField), forall (rho : GaloisRepresentation), SemistableAt curve local_field -> GaloisRepresentationOfCurve curve rho -> ReusableAssumptions curve -> SemistableModularityConclusion curve -> SemistableModularityRoute curve), forall (no_BridgeAxiom_dependency_law : forall (curve : EllipticCurvePackage), SemistableModularityRoute curve -> NoBridgeAxiomDependency curve), Q), Q"
    },
    {
      "declaration": "semistable_modularity_data_intro",
      "source_kind": "explicit_term",
      "term": "fun GaloisRepresentation => fun DeformationFunctor => fun DeformationRing => fun HeckeAlgebra => fun DeformationRepresents => fun HeckeDeformationComparison => fun R_eq_T => fun ResidualIrreducible => fun LocalCondition => fun MinimalCondition => fun NonMinimalCondition => fun ModularityAssumption => fun ModularityConclusion => fun DeepAssumption => fun NonFreyUseCase => fun UsefulOutsideFrey => fun lifting_data => fun EllipticCurvePackage => fun LocalField => fun SemistableAt => fun GaloisRepresentationOfCurve => fun ReusableAssumptions => fun SemistableModularityConclusion => fun SemistableModularityRoute => fun NoBridgeAxiomDependency => fun semistable_assumptions_law => fun semistable_conclusion_law => fun semistable_modularity_law => fun no_BridgeAxiom_dependency_law => fun (Q : Prop) => fun (mk : forall (lifting_out : @ModularityLiftingData GaloisRepresentation DeformationFunctor DeformationRing HeckeAlgebra DeformationRepresents HeckeDeformationComparison R_eq_T ResidualIrreducible LocalCondition MinimalCondition NonMinimalCondition ModularityAssumption ModularityConclusion DeepAssumption NonFreyUseCase UsefulOutsideFrey), forall (semistable_assumptions_law : forall (curve : EllipticCurvePackage), forall (local_field : LocalField), SemistableAt curve local_field -> ReusableAssumptions curve), forall (semistable_conclusion_law : forall (curve : EllipticCurvePackage), forall (rho : GaloisRepresentation), GaloisRepresentationOfCurve curve rho -> ModularityConclusion rho -> SemistableModularityConclusion curve), forall (semistable_modularity_law : forall (curve : EllipticCurvePackage), forall (local_field : LocalField), forall (rho : GaloisRepresentation), SemistableAt curve local_field -> GaloisRepresentationOfCurve curve rho -> ReusableAssumptions curve -> SemistableModularityConclusion curve -> SemistableModularityRoute curve), forall (no_BridgeAxiom_dependency_law : forall (curve : EllipticCurvePackage), SemistableModularityRoute curve -> NoBridgeAxiomDependency curve), Q) => mk lifting_data semistable_assumptions_law semistable_conclusion_law semistable_modularity_law no_BridgeAxiom_dependency_law"
    },
    {
      "declaration": "semistable_modularity_lifting_input_surface",
      "source_kind": "explicit_term",
      "term": "fun GaloisRepresentation => fun DeformationFunctor => fun DeformationRing => fun HeckeAlgebra => fun DeformationRepresents => fun HeckeDeformationComparison => fun R_eq_T => fun ResidualIrreducible => fun LocalCondition => fun MinimalCondition => fun NonMinimalCondition => fun ModularityAssumption => fun ModularityConclusion => fun DeepAssumption => fun NonFreyUseCase => fun UsefulOutsideFrey => fun lifting_data => fun EllipticCurvePackage => fun LocalField => fun SemistableAt => fun GaloisRepresentationOfCurve => fun ReusableAssumptions => fun SemistableModularityConclusion => fun SemistableModularityRoute => fun NoBridgeAxiomDependency => fun data => data (@ModularityLiftingData GaloisRepresentation DeformationFunctor DeformationRing HeckeAlgebra DeformationRepresents HeckeDeformationComparison R_eq_T ResidualIrreducible LocalCondition MinimalCondition NonMinimalCondition ModularityAssumption ModularityConclusion DeepAssumption NonFreyUseCase UsefulOutsideFrey) (fun (lifting_out : @ModularityLiftingData GaloisRepresentation DeformationFunctor DeformationRing HeckeAlgebra DeformationRepresents HeckeDeformationComparison R_eq_T ResidualIrreducible LocalCondition MinimalCondition NonMinimalCondition ModularityAssumption ModularityConclusion DeepAssumption NonFreyUseCase UsefulOutsideFrey) => fun (semistable_assumptions_law : forall (curve : EllipticCurvePackage), forall (local_field : LocalField), SemistableAt curve local_field -> ReusableAssumptions curve) => fun (semistable_conclusion_law : forall (curve : EllipticCurvePackage), forall (rho : GaloisRepresentation), GaloisRepresentationOfCurve curve rho -> ModularityConclusion rho -> SemistableModularityConclusion curve) => fun (semistable_modularity_law : forall (curve : EllipticCurvePackage), forall (local_field : LocalField), forall (rho : GaloisRepresentation), SemistableAt curve local_field -> GaloisRepresentationOfCurve curve rho -> ReusableAssumptions curve -> SemistableModularityConclusion curve -> SemistableModularityRoute curve) => fun (no_BridgeAxiom_dependency_law : forall (curve : EllipticCurvePackage), SemistableModularityRoute curve -> NoBridgeAxiomDependency curve) => lifting_out)"
    },
    {
      "declaration": "semistable_reusable_assumptions_surface",
      "source_kind": "explicit_term",
      "term": "fun GaloisRepresentation => fun DeformationFunctor => fun DeformationRing => fun HeckeAlgebra => fun DeformationRepresents => fun HeckeDeformationComparison => fun R_eq_T => fun ResidualIrreducible => fun LocalCondition => fun MinimalCondition => fun NonMinimalCondition => fun ModularityAssumption => fun ModularityConclusion => fun DeepAssumption => fun NonFreyUseCase => fun UsefulOutsideFrey => fun lifting_data => fun EllipticCurvePackage => fun LocalField => fun SemistableAt => fun GaloisRepresentationOfCurve => fun ReusableAssumptions => fun SemistableModularityConclusion => fun SemistableModularityRoute => fun NoBridgeAxiomDependency => fun data => data (forall (curve : EllipticCurvePackage), forall (local_field : LocalField), SemistableAt curve local_field -> ReusableAssumptions curve) (fun (lifting_out : @ModularityLiftingData GaloisRepresentation DeformationFunctor DeformationRing HeckeAlgebra DeformationRepresents HeckeDeformationComparison R_eq_T ResidualIrreducible LocalCondition MinimalCondition NonMinimalCondition ModularityAssumption ModularityConclusion DeepAssumption NonFreyUseCase UsefulOutsideFrey) => fun (semistable_assumptions_law : forall (curve : EllipticCurvePackage), forall (local_field : LocalField), SemistableAt curve local_field -> ReusableAssumptions curve) => fun (semistable_conclusion_law : forall (curve : EllipticCurvePackage), forall (rho : GaloisRepresentation), GaloisRepresentationOfCurve curve rho -> ModularityConclusion rho -> SemistableModularityConclusion curve) => fun (semistable_modularity_law : forall (curve : EllipticCurvePackage), forall (local_field : LocalField), forall (rho : GaloisRepresentation), SemistableAt curve local_field -> GaloisRepresentationOfCurve curve rho -> ReusableAssumptions curve -> SemistableModularityConclusion curve -> SemistableModularityRoute curve) => fun (no_BridgeAxiom_dependency_law : forall (curve : EllipticCurvePackage), SemistableModularityRoute curve -> NoBridgeAxiomDependency curve) => semistable_assumptions_law)"
    },
    {
      "declaration": "semistable_modularity_conclusion_surface",
      "source_kind": "explicit_term",
      "term": "fun GaloisRepresentation => fun DeformationFunctor => fun DeformationRing => fun HeckeAlgebra => fun DeformationRepresents => fun HeckeDeformationComparison => fun R_eq_T => fun ResidualIrreducible => fun LocalCondition => fun MinimalCondition => fun NonMinimalCondition => fun ModularityAssumption => fun ModularityConclusion => fun DeepAssumption => fun NonFreyUseCase => fun UsefulOutsideFrey => fun lifting_data => fun EllipticCurvePackage => fun LocalField => fun SemistableAt => fun GaloisRepresentationOfCurve => fun ReusableAssumptions => fun SemistableModularityConclusion => fun SemistableModularityRoute => fun NoBridgeAxiomDependency => fun data => data (forall (curve : EllipticCurvePackage), forall (rho : GaloisRepresentation), GaloisRepresentationOfCurve curve rho -> ModularityConclusion rho -> SemistableModularityConclusion curve) (fun (lifting_out : @ModularityLiftingData GaloisRepresentation DeformationFunctor DeformationRing HeckeAlgebra DeformationRepresents HeckeDeformationComparison R_eq_T ResidualIrreducible LocalCondition MinimalCondition NonMinimalCondition ModularityAssumption ModularityConclusion DeepAssumption NonFreyUseCase UsefulOutsideFrey) => fun (semistable_assumptions_law : forall (curve : EllipticCurvePackage), forall (local_field : LocalField), SemistableAt curve local_field -> ReusableAssumptions curve) => fun (semistable_conclusion_law : forall (curve : EllipticCurvePackage), forall (rho : GaloisRepresentation), GaloisRepresentationOfCurve curve rho -> ModularityConclusion rho -> SemistableModularityConclusion curve) => fun (semistable_modularity_law : forall (curve : EllipticCurvePackage), forall (local_field : LocalField), forall (rho : GaloisRepresentation), SemistableAt curve local_field -> GaloisRepresentationOfCurve curve rho -> ReusableAssumptions curve -> SemistableModularityConclusion curve -> SemistableModularityRoute curve) => fun (no_BridgeAxiom_dependency_law : forall (curve : EllipticCurvePackage), SemistableModularityRoute curve -> NoBridgeAxiomDependency curve) => semistable_conclusion_law)"
    },
    {
      "declaration": "semistable_modularity_route_surface",
      "source_kind": "explicit_term",
      "term": "fun GaloisRepresentation => fun DeformationFunctor => fun DeformationRing => fun HeckeAlgebra => fun DeformationRepresents => fun HeckeDeformationComparison => fun R_eq_T => fun ResidualIrreducible => fun LocalCondition => fun MinimalCondition => fun NonMinimalCondition => fun ModularityAssumption => fun ModularityConclusion => fun DeepAssumption => fun NonFreyUseCase => fun UsefulOutsideFrey => fun lifting_data => fun EllipticCurvePackage => fun LocalField => fun SemistableAt => fun GaloisRepresentationOfCurve => fun ReusableAssumptions => fun SemistableModularityConclusion => fun SemistableModularityRoute => fun NoBridgeAxiomDependency => fun data => data (forall (curve : EllipticCurvePackage), forall (local_field : LocalField), forall (rho : GaloisRepresentation), SemistableAt curve local_field -> GaloisRepresentationOfCurve curve rho -> ReusableAssumptions curve -> SemistableModularityConclusion curve -> SemistableModularityRoute curve) (fun (lifting_out : @ModularityLiftingData GaloisRepresentation DeformationFunctor DeformationRing HeckeAlgebra DeformationRepresents HeckeDeformationComparison R_eq_T ResidualIrreducible LocalCondition MinimalCondition NonMinimalCondition ModularityAssumption ModularityConclusion DeepAssumption NonFreyUseCase UsefulOutsideFrey) => fun (semistable_assumptions_law : forall (curve : EllipticCurvePackage), forall (local_field : LocalField), SemistableAt curve local_field -> ReusableAssumptions curve) => fun (semistable_conclusion_law : forall (curve : EllipticCurvePackage), forall (rho : GaloisRepresentation), GaloisRepresentationOfCurve curve rho -> ModularityConclusion rho -> SemistableModularityConclusion curve) => fun (semistable_modularity_law : forall (curve : EllipticCurvePackage), forall (local_field : LocalField), forall (rho : GaloisRepresentation), SemistableAt curve local_field -> GaloisRepresentationOfCurve curve rho -> ReusableAssumptions curve -> SemistableModularityConclusion curve -> SemistableModularityRoute curve) => fun (no_BridgeAxiom_dependency_law : forall (curve : EllipticCurvePackage), SemistableModularityRoute curve -> NoBridgeAxiomDependency curve) => semistable_modularity_law)"
    },
    {
      "declaration": "semistable_modularity_no_BridgeAxiom_dependency",
      "source_kind": "explicit_term",
      "term": "fun GaloisRepresentation => fun DeformationFunctor => fun DeformationRing => fun HeckeAlgebra => fun DeformationRepresents => fun HeckeDeformationComparison => fun R_eq_T => fun ResidualIrreducible => fun LocalCondition => fun MinimalCondition => fun NonMinimalCondition => fun ModularityAssumption => fun ModularityConclusion => fun DeepAssumption => fun NonFreyUseCase => fun UsefulOutsideFrey => fun lifting_data => fun EllipticCurvePackage => fun LocalField => fun SemistableAt => fun GaloisRepresentationOfCurve => fun ReusableAssumptions => fun SemistableModularityConclusion => fun SemistableModularityRoute => fun NoBridgeAxiomDependency => fun data => data (forall (curve : EllipticCurvePackage), SemistableModularityRoute curve -> NoBridgeAxiomDependency curve) (fun (lifting_out : @ModularityLiftingData GaloisRepresentation DeformationFunctor DeformationRing HeckeAlgebra DeformationRepresents HeckeDeformationComparison R_eq_T ResidualIrreducible LocalCondition MinimalCondition NonMinimalCondition ModularityAssumption ModularityConclusion DeepAssumption NonFreyUseCase UsefulOutsideFrey) => fun (semistable_assumptions_law : forall (curve : EllipticCurvePackage), forall (local_field : LocalField), SemistableAt curve local_field -> ReusableAssumptions curve) => fun (semistable_conclusion_law : forall (curve : EllipticCurvePackage), forall (rho : GaloisRepresentation), GaloisRepresentationOfCurve curve rho -> ModularityConclusion rho -> SemistableModularityConclusion curve) => fun (semistable_modularity_law : forall (curve : EllipticCurvePackage), forall (local_field : LocalField), forall (rho : GaloisRepresentation), SemistableAt curve local_field -> GaloisRepresentationOfCurve curve rho -> ReusableAssumptions curve -> SemistableModularityConclusion curve -> SemistableModularityRoute curve) => fun (no_BridgeAxiom_dependency_law : forall (curve : EllipticCurvePackage), SemistableModularityRoute curve -> NoBridgeAxiomDependency curve) => no_BridgeAxiom_dependency_law)"
    }
  ],
  "acceptance": {
    "required": ["decode_module_cert", "verify_module_cert"],
    "accepted_artifact": "Proofs/Ai/Modularity/Semistable/certificate.npcert"
  }
}
