{
  "schema": "npa-ai-proof-meta-v0.1",
  "module": "Proofs.Ai.Algebra.AbstractKrullTheorem",
  "source": "Proofs/Ai/Algebra/AbstractKrullTheorem/source.npa",
  "certificate": "Proofs/Ai/Algebra/AbstractKrullTheorem/certificate.npcert",
  "producer_profile": "human-surface-explicit-term",
  "trusted_status": "verified_by_certificate",
  "source_sha256": "sha256:610280533c14d9d7c32b604cf69ecff839e7a9b46b795fcdbe3edd13b0d1a649",
  "certificate_file_sha256": "sha256:1e93b39cc711e9240f3bcc90fe498ba701d0c5e06e58692995c0246b1919dde5",
  "export_hash": "sha256:bfbc78f435db04f8cf7f49878187cf6b9cb05b7948b0863c3382679ff0384ce6",
  "axiom_report_hash": "sha256:c719d1be9850d3cfc41fde0acfd7e6f6416da3180df18594cfb1c789cf73c02f",
  "certificate_hash": "sha256:66c51c3b30c7fc81301dc3a90bb2961efb813cfaab3337f11d67a8106e222e9f",
  "imports": ["Std.Logic.Eq", "Proofs.Ai.Algebra.AbstractRing", "Proofs.Ai.Algebra.AbstractHilbertBasisTheorem"],
  "axioms": [],
  "declarations": [
    { "name": "KrlFalse", "kind": "def" },
    { "name": "KrlNot", "kind": "def" },
    { "name": "IdealLe", "kind": "def" },
    { "name": "ProperIdeal", "kind": "def" },
    { "name": "MaximalIdeal", "kind": "def" },
    { "name": "MaximalIdealOver", "kind": "def" },
    { "name": "KrullConstructionArgs", "kind": "def" },
    { "name": "KrullTheorem", "kind": "def" },
    { "name": "ideal_le_refl", "kind": "theorem" },
    { "name": "ideal_le_trans", "kind": "theorem" },
    { "name": "maximal_ideal_intro", "kind": "theorem" },
    { "name": "maximal_ideal_laws", "kind": "theorem" },
    { "name": "maximal_ideal_proper", "kind": "theorem" },
    { "name": "maximal_ideal_of_proper_overideal_le", "kind": "theorem" },
    { "name": "maximal_ideal_over_intro", "kind": "theorem" },
    { "name": "maximal_ideal_over_contains", "kind": "theorem" },
    { "name": "maximal_ideal_over_maximal", "kind": "theorem" },
    { "name": "krull_construction_args_intro", "kind": "theorem" },
    { "name": "krull_maximal_ideal_exists", "kind": "theorem" },
    { "name": "krull_maximal_ideal_contains", "kind": "theorem" },
    { "name": "krull_maximal_ideal_is_maximal", "kind": "theorem" },
    { "name": "krull_theorem", "kind": "theorem" }
  ],
  "trust_boundary": "source, replay, and metadata are non-trusted sidecars; only the canonical certificate verified by npa-cert is accepted"
}
