{
  "schema": "npa-ai-proof-replay-v0.1",
  "module": "Proofs.Ai.NumberTheory.AutomorphicL",
  "trusted": false,
  "profile": "explicit_term_source_certificate_handoff",
  "steps": [
    {
      "declaration": "AutomorphicLData",
      "source_kind": "explicit_def_value",
      "term": "fun Family => fun Complex => fun Coeff => fun Prime => fun LFunction => fun CoefficientField => fun InCoefficientField => fun coefficient_field => fun LocalFactor => fun LocalFactorData => fun EulerProduct => fun EulerProductData => fun AnalyticDomain => fun Normalization => fun AnalyticContinuation => fun FunctionalEquation => fun NoConjecturalL2 => fun HasseWeilSource => fun HasseWeilLFunction => fun AutomorphicSource => fun AutomorphicLFunction => fun HeckeCharacter => fun HeckeLocalFactorNormalized => fun HeckeEulerProductCompatible => fun HeckeAutomorphicNormalization => fun HeckeLFunction => fun AutomorphicRepresentation => fun CuspidalRepresentation => fun AutomorphicAnalyticAssumptions => fun RankinSelbergProduct => fun RankinSelbergAnalyticSurface => fun LanglandsShahidiNormalization => fun ConverseTheoremHypotheses => fun TraceFormulaAssumptions => fun TraceFormulaMap => fun SemistableModularityCompatibility => forall (Q : Prop), forall (mk : forall (general_l_function_data : @LFunctionData Family Complex Coeff Prime LFunction CoefficientField InCoefficientField coefficient_field LocalFactor LocalFactorData EulerProduct EulerProductData AnalyticDomain Normalization AnalyticContinuation FunctionalEquation NoConjecturalL2 HasseWeilSource HasseWeilLFunction AutomorphicSource AutomorphicLFunction), forall (hecke_l_data : @HeckeLData Family Complex Coeff Prime LFunction CoefficientField InCoefficientField coefficient_field LocalFactor LocalFactorData EulerProduct EulerProductData AnalyticDomain Normalization AnalyticContinuation FunctionalEquation NoConjecturalL2 HasseWeilSource HasseWeilLFunction AutomorphicSource AutomorphicLFunction HeckeCharacter HeckeLocalFactorNormalized HeckeEulerProductCompatible HeckeAutomorphicNormalization HeckeLFunction), forall (cuspidal_representation_law : forall (pi : Family), CuspidalRepresentation pi -> AutomorphicRepresentation pi), forall (automorphic_l_function_law : forall (pi : Family), AutomorphicRepresentation pi -> AutomorphicLFunction pi), forall (rankin_selberg_product_law : forall (pi : Family), forall (sigma : Family), AutomorphicRepresentation pi -> AutomorphicRepresentation sigma -> RankinSelbergProduct pi sigma), forall (rankin_selberg_analytic_law : forall (pi : Family), forall (sigma : Family), forall (s : Complex), RankinSelbergProduct pi sigma -> AutomorphicAnalyticAssumptions pi -> AutomorphicAnalyticAssumptions sigma -> RankinSelbergAnalyticSurface pi sigma s), forall (langlands_shahidi_normalization_law : forall (pi : Family), AutomorphicRepresentation pi -> LanglandsShahidiNormalization pi), forall (converse_theorem_law : forall (pi : Family), ConverseTheoremHypotheses pi -> AutomorphicRepresentation pi), forall (trace_formula_map_law : forall (pi : Family), AutomorphicRepresentation pi -> TraceFormulaAssumptions pi -> TraceFormulaMap pi), forall (analytic_continuation_l1_law : forall (pi : Family), AutomorphicRepresentation pi -> AutomorphicAnalyticAssumptions pi -> AnalyticContinuation pi (LFunction pi)), forall (semistable_modularity_compatibility_law : forall (pi : Family), SemistableModularityCompatibility pi -> AutomorphicRepresentation pi), Q), Q"
    },
    {
      "declaration": "automorphic_l_data_intro",
      "source_kind": "explicit_term",
      "term": "fun Family => fun Complex => fun Coeff => fun Prime => fun LFunction => fun CoefficientField => fun InCoefficientField => fun coefficient_field => fun LocalFactor => fun LocalFactorData => fun EulerProduct => fun EulerProductData => fun AnalyticDomain => fun Normalization => fun AnalyticContinuation => fun FunctionalEquation => fun NoConjecturalL2 => fun HasseWeilSource => fun HasseWeilLFunction => fun AutomorphicSource => fun AutomorphicLFunction => fun HeckeCharacter => fun HeckeLocalFactorNormalized => fun HeckeEulerProductCompatible => fun HeckeAutomorphicNormalization => fun HeckeLFunction => fun AutomorphicRepresentation => fun CuspidalRepresentation => fun AutomorphicAnalyticAssumptions => fun RankinSelbergProduct => fun RankinSelbergAnalyticSurface => fun LanglandsShahidiNormalization => fun ConverseTheoremHypotheses => fun TraceFormulaAssumptions => fun TraceFormulaMap => fun SemistableModularityCompatibility => fun general_l_function_data => fun hecke_l_data => fun cuspidal_representation_law => fun automorphic_l_function_law => fun rankin_selberg_product_law => fun rankin_selberg_analytic_law => fun langlands_shahidi_normalization_law => fun converse_theorem_law => fun trace_formula_map_law => fun analytic_continuation_l1_law => fun semistable_modularity_compatibility_law => fun (Q : Prop) => fun (mk : forall (general_l_function_data : @LFunctionData Family Complex Coeff Prime LFunction CoefficientField InCoefficientField coefficient_field LocalFactor LocalFactorData EulerProduct EulerProductData AnalyticDomain Normalization AnalyticContinuation FunctionalEquation NoConjecturalL2 HasseWeilSource HasseWeilLFunction AutomorphicSource AutomorphicLFunction), forall (hecke_l_data : @HeckeLData Family Complex Coeff Prime LFunction CoefficientField InCoefficientField coefficient_field LocalFactor LocalFactorData EulerProduct EulerProductData AnalyticDomain Normalization AnalyticContinuation FunctionalEquation NoConjecturalL2 HasseWeilSource HasseWeilLFunction AutomorphicSource AutomorphicLFunction HeckeCharacter HeckeLocalFactorNormalized HeckeEulerProductCompatible HeckeAutomorphicNormalization HeckeLFunction), forall (cuspidal_representation_law : forall (pi : Family), CuspidalRepresentation pi -> AutomorphicRepresentation pi), forall (automorphic_l_function_law : forall (pi : Family), AutomorphicRepresentation pi -> AutomorphicLFunction pi), forall (rankin_selberg_product_law : forall (pi : Family), forall (sigma : Family), AutomorphicRepresentation pi -> AutomorphicRepresentation sigma -> RankinSelbergProduct pi sigma), forall (rankin_selberg_analytic_law : forall (pi : Family), forall (sigma : Family), forall (s : Complex), RankinSelbergProduct pi sigma -> AutomorphicAnalyticAssumptions pi -> AutomorphicAnalyticAssumptions sigma -> RankinSelbergAnalyticSurface pi sigma s), forall (langlands_shahidi_normalization_law : forall (pi : Family), AutomorphicRepresentation pi -> LanglandsShahidiNormalization pi), forall (converse_theorem_law : forall (pi : Family), ConverseTheoremHypotheses pi -> AutomorphicRepresentation pi), forall (trace_formula_map_law : forall (pi : Family), AutomorphicRepresentation pi -> TraceFormulaAssumptions pi -> TraceFormulaMap pi), forall (analytic_continuation_l1_law : forall (pi : Family), AutomorphicRepresentation pi -> AutomorphicAnalyticAssumptions pi -> AnalyticContinuation pi (LFunction pi)), forall (semistable_modularity_compatibility_law : forall (pi : Family), SemistableModularityCompatibility pi -> AutomorphicRepresentation pi), Q) => mk general_l_function_data hecke_l_data cuspidal_representation_law automorphic_l_function_law rankin_selberg_product_law rankin_selberg_analytic_law langlands_shahidi_normalization_law converse_theorem_law trace_formula_map_law analytic_continuation_l1_law semistable_modularity_compatibility_law"
    },
    {
      "declaration": "automorphic_l_general_l_function_data",
      "source_kind": "explicit_term",
      "term": "fun Family => fun Complex => fun Coeff => fun Prime => fun LFunction => fun CoefficientField => fun InCoefficientField => fun coefficient_field => fun LocalFactor => fun LocalFactorData => fun EulerProduct => fun EulerProductData => fun AnalyticDomain => fun Normalization => fun AnalyticContinuation => fun FunctionalEquation => fun NoConjecturalL2 => fun HasseWeilSource => fun HasseWeilLFunction => fun AutomorphicSource => fun AutomorphicLFunction => fun HeckeCharacter => fun HeckeLocalFactorNormalized => fun HeckeEulerProductCompatible => fun HeckeAutomorphicNormalization => fun HeckeLFunction => fun AutomorphicRepresentation => fun CuspidalRepresentation => fun AutomorphicAnalyticAssumptions => fun RankinSelbergProduct => fun RankinSelbergAnalyticSurface => fun LanglandsShahidiNormalization => fun ConverseTheoremHypotheses => fun TraceFormulaAssumptions => fun TraceFormulaMap => fun SemistableModularityCompatibility => fun data => data (@LFunctionData Family Complex Coeff Prime LFunction CoefficientField InCoefficientField coefficient_field LocalFactor LocalFactorData EulerProduct EulerProductData AnalyticDomain Normalization AnalyticContinuation FunctionalEquation NoConjecturalL2 HasseWeilSource HasseWeilLFunction AutomorphicSource AutomorphicLFunction) (fun (general_l_function_data : @LFunctionData Family Complex Coeff Prime LFunction CoefficientField InCoefficientField coefficient_field LocalFactor LocalFactorData EulerProduct EulerProductData AnalyticDomain Normalization AnalyticContinuation FunctionalEquation NoConjecturalL2 HasseWeilSource HasseWeilLFunction AutomorphicSource AutomorphicLFunction) => fun (hecke_l_data : @HeckeLData Family Complex Coeff Prime LFunction CoefficientField InCoefficientField coefficient_field LocalFactor LocalFactorData EulerProduct EulerProductData AnalyticDomain Normalization AnalyticContinuation FunctionalEquation NoConjecturalL2 HasseWeilSource HasseWeilLFunction AutomorphicSource AutomorphicLFunction HeckeCharacter HeckeLocalFactorNormalized HeckeEulerProductCompatible HeckeAutomorphicNormalization HeckeLFunction) => fun (cuspidal_representation_law : forall (pi : Family), CuspidalRepresentation pi -> AutomorphicRepresentation pi) => fun (automorphic_l_function_law : forall (pi : Family), AutomorphicRepresentation pi -> AutomorphicLFunction pi) => fun (rankin_selberg_product_law : forall (pi : Family), forall (sigma : Family), AutomorphicRepresentation pi -> AutomorphicRepresentation sigma -> RankinSelbergProduct pi sigma) => fun (rankin_selberg_analytic_law : forall (pi : Family), forall (sigma : Family), forall (s : Complex), RankinSelbergProduct pi sigma -> AutomorphicAnalyticAssumptions pi -> AutomorphicAnalyticAssumptions sigma -> RankinSelbergAnalyticSurface pi sigma s) => fun (langlands_shahidi_normalization_law : forall (pi : Family), AutomorphicRepresentation pi -> LanglandsShahidiNormalization pi) => fun (converse_theorem_law : forall (pi : Family), ConverseTheoremHypotheses pi -> AutomorphicRepresentation pi) => fun (trace_formula_map_law : forall (pi : Family), AutomorphicRepresentation pi -> TraceFormulaAssumptions pi -> TraceFormulaMap pi) => fun (analytic_continuation_l1_law : forall (pi : Family), AutomorphicRepresentation pi -> AutomorphicAnalyticAssumptions pi -> AnalyticContinuation pi (LFunction pi)) => fun (semistable_modularity_compatibility_law : forall (pi : Family), SemistableModularityCompatibility pi -> AutomorphicRepresentation pi) => general_l_function_data)"
    },
    {
      "declaration": "automorphic_l_hecke_l_data",
      "source_kind": "explicit_term",
      "term": "fun Family => fun Complex => fun Coeff => fun Prime => fun LFunction => fun CoefficientField => fun InCoefficientField => fun coefficient_field => fun LocalFactor => fun LocalFactorData => fun EulerProduct => fun EulerProductData => fun AnalyticDomain => fun Normalization => fun AnalyticContinuation => fun FunctionalEquation => fun NoConjecturalL2 => fun HasseWeilSource => fun HasseWeilLFunction => fun AutomorphicSource => fun AutomorphicLFunction => fun HeckeCharacter => fun HeckeLocalFactorNormalized => fun HeckeEulerProductCompatible => fun HeckeAutomorphicNormalization => fun HeckeLFunction => fun AutomorphicRepresentation => fun CuspidalRepresentation => fun AutomorphicAnalyticAssumptions => fun RankinSelbergProduct => fun RankinSelbergAnalyticSurface => fun LanglandsShahidiNormalization => fun ConverseTheoremHypotheses => fun TraceFormulaAssumptions => fun TraceFormulaMap => fun SemistableModularityCompatibility => fun data => data (@HeckeLData Family Complex Coeff Prime LFunction CoefficientField InCoefficientField coefficient_field LocalFactor LocalFactorData EulerProduct EulerProductData AnalyticDomain Normalization AnalyticContinuation FunctionalEquation NoConjecturalL2 HasseWeilSource HasseWeilLFunction AutomorphicSource AutomorphicLFunction HeckeCharacter HeckeLocalFactorNormalized HeckeEulerProductCompatible HeckeAutomorphicNormalization HeckeLFunction) (fun (general_l_function_data : @LFunctionData Family Complex Coeff Prime LFunction CoefficientField InCoefficientField coefficient_field LocalFactor LocalFactorData EulerProduct EulerProductData AnalyticDomain Normalization AnalyticContinuation FunctionalEquation NoConjecturalL2 HasseWeilSource HasseWeilLFunction AutomorphicSource AutomorphicLFunction) => fun (hecke_l_data : @HeckeLData Family Complex Coeff Prime LFunction CoefficientField InCoefficientField coefficient_field LocalFactor LocalFactorData EulerProduct EulerProductData AnalyticDomain Normalization AnalyticContinuation FunctionalEquation NoConjecturalL2 HasseWeilSource HasseWeilLFunction AutomorphicSource AutomorphicLFunction HeckeCharacter HeckeLocalFactorNormalized HeckeEulerProductCompatible HeckeAutomorphicNormalization HeckeLFunction) => fun (cuspidal_representation_law : forall (pi : Family), CuspidalRepresentation pi -> AutomorphicRepresentation pi) => fun (automorphic_l_function_law : forall (pi : Family), AutomorphicRepresentation pi -> AutomorphicLFunction pi) => fun (rankin_selberg_product_law : forall (pi : Family), forall (sigma : Family), AutomorphicRepresentation pi -> AutomorphicRepresentation sigma -> RankinSelbergProduct pi sigma) => fun (rankin_selberg_analytic_law : forall (pi : Family), forall (sigma : Family), forall (s : Complex), RankinSelbergProduct pi sigma -> AutomorphicAnalyticAssumptions pi -> AutomorphicAnalyticAssumptions sigma -> RankinSelbergAnalyticSurface pi sigma s) => fun (langlands_shahidi_normalization_law : forall (pi : Family), AutomorphicRepresentation pi -> LanglandsShahidiNormalization pi) => fun (converse_theorem_law : forall (pi : Family), ConverseTheoremHypotheses pi -> AutomorphicRepresentation pi) => fun (trace_formula_map_law : forall (pi : Family), AutomorphicRepresentation pi -> TraceFormulaAssumptions pi -> TraceFormulaMap pi) => fun (analytic_continuation_l1_law : forall (pi : Family), AutomorphicRepresentation pi -> AutomorphicAnalyticAssumptions pi -> AnalyticContinuation pi (LFunction pi)) => fun (semistable_modularity_compatibility_law : forall (pi : Family), SemistableModularityCompatibility pi -> AutomorphicRepresentation pi) => hecke_l_data)"
    },
    {
      "declaration": "cuspidal_representation_is_automorphic_surface",
      "source_kind": "explicit_term",
      "term": "fun Family => fun Complex => fun Coeff => fun Prime => fun LFunction => fun CoefficientField => fun InCoefficientField => fun coefficient_field => fun LocalFactor => fun LocalFactorData => fun EulerProduct => fun EulerProductData => fun AnalyticDomain => fun Normalization => fun AnalyticContinuation => fun FunctionalEquation => fun NoConjecturalL2 => fun HasseWeilSource => fun HasseWeilLFunction => fun AutomorphicSource => fun AutomorphicLFunction => fun HeckeCharacter => fun HeckeLocalFactorNormalized => fun HeckeEulerProductCompatible => fun HeckeAutomorphicNormalization => fun HeckeLFunction => fun AutomorphicRepresentation => fun CuspidalRepresentation => fun AutomorphicAnalyticAssumptions => fun RankinSelbergProduct => fun RankinSelbergAnalyticSurface => fun LanglandsShahidiNormalization => fun ConverseTheoremHypotheses => fun TraceFormulaAssumptions => fun TraceFormulaMap => fun SemistableModularityCompatibility => fun data => data (forall (pi : Family), CuspidalRepresentation pi -> AutomorphicRepresentation pi) (fun (general_l_function_data : @LFunctionData Family Complex Coeff Prime LFunction CoefficientField InCoefficientField coefficient_field LocalFactor LocalFactorData EulerProduct EulerProductData AnalyticDomain Normalization AnalyticContinuation FunctionalEquation NoConjecturalL2 HasseWeilSource HasseWeilLFunction AutomorphicSource AutomorphicLFunction) => fun (hecke_l_data : @HeckeLData Family Complex Coeff Prime LFunction CoefficientField InCoefficientField coefficient_field LocalFactor LocalFactorData EulerProduct EulerProductData AnalyticDomain Normalization AnalyticContinuation FunctionalEquation NoConjecturalL2 HasseWeilSource HasseWeilLFunction AutomorphicSource AutomorphicLFunction HeckeCharacter HeckeLocalFactorNormalized HeckeEulerProductCompatible HeckeAutomorphicNormalization HeckeLFunction) => fun (cuspidal_representation_law : forall (pi : Family), CuspidalRepresentation pi -> AutomorphicRepresentation pi) => fun (automorphic_l_function_law : forall (pi : Family), AutomorphicRepresentation pi -> AutomorphicLFunction pi) => fun (rankin_selberg_product_law : forall (pi : Family), forall (sigma : Family), AutomorphicRepresentation pi -> AutomorphicRepresentation sigma -> RankinSelbergProduct pi sigma) => fun (rankin_selberg_analytic_law : forall (pi : Family), forall (sigma : Family), forall (s : Complex), RankinSelbergProduct pi sigma -> AutomorphicAnalyticAssumptions pi -> AutomorphicAnalyticAssumptions sigma -> RankinSelbergAnalyticSurface pi sigma s) => fun (langlands_shahidi_normalization_law : forall (pi : Family), AutomorphicRepresentation pi -> LanglandsShahidiNormalization pi) => fun (converse_theorem_law : forall (pi : Family), ConverseTheoremHypotheses pi -> AutomorphicRepresentation pi) => fun (trace_formula_map_law : forall (pi : Family), AutomorphicRepresentation pi -> TraceFormulaAssumptions pi -> TraceFormulaMap pi) => fun (analytic_continuation_l1_law : forall (pi : Family), AutomorphicRepresentation pi -> AutomorphicAnalyticAssumptions pi -> AnalyticContinuation pi (LFunction pi)) => fun (semistable_modularity_compatibility_law : forall (pi : Family), SemistableModularityCompatibility pi -> AutomorphicRepresentation pi) => cuspidal_representation_law)"
    },
    {
      "declaration": "automorphic_representation_l_function_surface",
      "source_kind": "explicit_term",
      "term": "fun Family => fun Complex => fun Coeff => fun Prime => fun LFunction => fun CoefficientField => fun InCoefficientField => fun coefficient_field => fun LocalFactor => fun LocalFactorData => fun EulerProduct => fun EulerProductData => fun AnalyticDomain => fun Normalization => fun AnalyticContinuation => fun FunctionalEquation => fun NoConjecturalL2 => fun HasseWeilSource => fun HasseWeilLFunction => fun AutomorphicSource => fun AutomorphicLFunction => fun HeckeCharacter => fun HeckeLocalFactorNormalized => fun HeckeEulerProductCompatible => fun HeckeAutomorphicNormalization => fun HeckeLFunction => fun AutomorphicRepresentation => fun CuspidalRepresentation => fun AutomorphicAnalyticAssumptions => fun RankinSelbergProduct => fun RankinSelbergAnalyticSurface => fun LanglandsShahidiNormalization => fun ConverseTheoremHypotheses => fun TraceFormulaAssumptions => fun TraceFormulaMap => fun SemistableModularityCompatibility => fun data => data (forall (pi : Family), AutomorphicRepresentation pi -> AutomorphicLFunction pi) (fun (general_l_function_data : @LFunctionData Family Complex Coeff Prime LFunction CoefficientField InCoefficientField coefficient_field LocalFactor LocalFactorData EulerProduct EulerProductData AnalyticDomain Normalization AnalyticContinuation FunctionalEquation NoConjecturalL2 HasseWeilSource HasseWeilLFunction AutomorphicSource AutomorphicLFunction) => fun (hecke_l_data : @HeckeLData Family Complex Coeff Prime LFunction CoefficientField InCoefficientField coefficient_field LocalFactor LocalFactorData EulerProduct EulerProductData AnalyticDomain Normalization AnalyticContinuation FunctionalEquation NoConjecturalL2 HasseWeilSource HasseWeilLFunction AutomorphicSource AutomorphicLFunction HeckeCharacter HeckeLocalFactorNormalized HeckeEulerProductCompatible HeckeAutomorphicNormalization HeckeLFunction) => fun (cuspidal_representation_law : forall (pi : Family), CuspidalRepresentation pi -> AutomorphicRepresentation pi) => fun (automorphic_l_function_law : forall (pi : Family), AutomorphicRepresentation pi -> AutomorphicLFunction pi) => fun (rankin_selberg_product_law : forall (pi : Family), forall (sigma : Family), AutomorphicRepresentation pi -> AutomorphicRepresentation sigma -> RankinSelbergProduct pi sigma) => fun (rankin_selberg_analytic_law : forall (pi : Family), forall (sigma : Family), forall (s : Complex), RankinSelbergProduct pi sigma -> AutomorphicAnalyticAssumptions pi -> AutomorphicAnalyticAssumptions sigma -> RankinSelbergAnalyticSurface pi sigma s) => fun (langlands_shahidi_normalization_law : forall (pi : Family), AutomorphicRepresentation pi -> LanglandsShahidiNormalization pi) => fun (converse_theorem_law : forall (pi : Family), ConverseTheoremHypotheses pi -> AutomorphicRepresentation pi) => fun (trace_formula_map_law : forall (pi : Family), AutomorphicRepresentation pi -> TraceFormulaAssumptions pi -> TraceFormulaMap pi) => fun (analytic_continuation_l1_law : forall (pi : Family), AutomorphicRepresentation pi -> AutomorphicAnalyticAssumptions pi -> AnalyticContinuation pi (LFunction pi)) => fun (semistable_modularity_compatibility_law : forall (pi : Family), SemistableModularityCompatibility pi -> AutomorphicRepresentation pi) => automorphic_l_function_law)"
    },
    {
      "declaration": "rankin_selberg_product_surface",
      "source_kind": "explicit_term",
      "term": "fun Family => fun Complex => fun Coeff => fun Prime => fun LFunction => fun CoefficientField => fun InCoefficientField => fun coefficient_field => fun LocalFactor => fun LocalFactorData => fun EulerProduct => fun EulerProductData => fun AnalyticDomain => fun Normalization => fun AnalyticContinuation => fun FunctionalEquation => fun NoConjecturalL2 => fun HasseWeilSource => fun HasseWeilLFunction => fun AutomorphicSource => fun AutomorphicLFunction => fun HeckeCharacter => fun HeckeLocalFactorNormalized => fun HeckeEulerProductCompatible => fun HeckeAutomorphicNormalization => fun HeckeLFunction => fun AutomorphicRepresentation => fun CuspidalRepresentation => fun AutomorphicAnalyticAssumptions => fun RankinSelbergProduct => fun RankinSelbergAnalyticSurface => fun LanglandsShahidiNormalization => fun ConverseTheoremHypotheses => fun TraceFormulaAssumptions => fun TraceFormulaMap => fun SemistableModularityCompatibility => fun data => data (forall (pi : Family), forall (sigma : Family), AutomorphicRepresentation pi -> AutomorphicRepresentation sigma -> RankinSelbergProduct pi sigma) (fun (general_l_function_data : @LFunctionData Family Complex Coeff Prime LFunction CoefficientField InCoefficientField coefficient_field LocalFactor LocalFactorData EulerProduct EulerProductData AnalyticDomain Normalization AnalyticContinuation FunctionalEquation NoConjecturalL2 HasseWeilSource HasseWeilLFunction AutomorphicSource AutomorphicLFunction) => fun (hecke_l_data : @HeckeLData Family Complex Coeff Prime LFunction CoefficientField InCoefficientField coefficient_field LocalFactor LocalFactorData EulerProduct EulerProductData AnalyticDomain Normalization AnalyticContinuation FunctionalEquation NoConjecturalL2 HasseWeilSource HasseWeilLFunction AutomorphicSource AutomorphicLFunction HeckeCharacter HeckeLocalFactorNormalized HeckeEulerProductCompatible HeckeAutomorphicNormalization HeckeLFunction) => fun (cuspidal_representation_law : forall (pi : Family), CuspidalRepresentation pi -> AutomorphicRepresentation pi) => fun (automorphic_l_function_law : forall (pi : Family), AutomorphicRepresentation pi -> AutomorphicLFunction pi) => fun (rankin_selberg_product_law : forall (pi : Family), forall (sigma : Family), AutomorphicRepresentation pi -> AutomorphicRepresentation sigma -> RankinSelbergProduct pi sigma) => fun (rankin_selberg_analytic_law : forall (pi : Family), forall (sigma : Family), forall (s : Complex), RankinSelbergProduct pi sigma -> AutomorphicAnalyticAssumptions pi -> AutomorphicAnalyticAssumptions sigma -> RankinSelbergAnalyticSurface pi sigma s) => fun (langlands_shahidi_normalization_law : forall (pi : Family), AutomorphicRepresentation pi -> LanglandsShahidiNormalization pi) => fun (converse_theorem_law : forall (pi : Family), ConverseTheoremHypotheses pi -> AutomorphicRepresentation pi) => fun (trace_formula_map_law : forall (pi : Family), AutomorphicRepresentation pi -> TraceFormulaAssumptions pi -> TraceFormulaMap pi) => fun (analytic_continuation_l1_law : forall (pi : Family), AutomorphicRepresentation pi -> AutomorphicAnalyticAssumptions pi -> AnalyticContinuation pi (LFunction pi)) => fun (semistable_modularity_compatibility_law : forall (pi : Family), SemistableModularityCompatibility pi -> AutomorphicRepresentation pi) => rankin_selberg_product_law)"
    },
    {
      "declaration": "rankin_selberg_analytic_surface",
      "source_kind": "explicit_term",
      "term": "fun Family => fun Complex => fun Coeff => fun Prime => fun LFunction => fun CoefficientField => fun InCoefficientField => fun coefficient_field => fun LocalFactor => fun LocalFactorData => fun EulerProduct => fun EulerProductData => fun AnalyticDomain => fun Normalization => fun AnalyticContinuation => fun FunctionalEquation => fun NoConjecturalL2 => fun HasseWeilSource => fun HasseWeilLFunction => fun AutomorphicSource => fun AutomorphicLFunction => fun HeckeCharacter => fun HeckeLocalFactorNormalized => fun HeckeEulerProductCompatible => fun HeckeAutomorphicNormalization => fun HeckeLFunction => fun AutomorphicRepresentation => fun CuspidalRepresentation => fun AutomorphicAnalyticAssumptions => fun RankinSelbergProduct => fun RankinSelbergAnalyticSurface => fun LanglandsShahidiNormalization => fun ConverseTheoremHypotheses => fun TraceFormulaAssumptions => fun TraceFormulaMap => fun SemistableModularityCompatibility => fun data => data (forall (pi : Family), forall (sigma : Family), forall (s : Complex), RankinSelbergProduct pi sigma -> AutomorphicAnalyticAssumptions pi -> AutomorphicAnalyticAssumptions sigma -> RankinSelbergAnalyticSurface pi sigma s) (fun (general_l_function_data : @LFunctionData Family Complex Coeff Prime LFunction CoefficientField InCoefficientField coefficient_field LocalFactor LocalFactorData EulerProduct EulerProductData AnalyticDomain Normalization AnalyticContinuation FunctionalEquation NoConjecturalL2 HasseWeilSource HasseWeilLFunction AutomorphicSource AutomorphicLFunction) => fun (hecke_l_data : @HeckeLData Family Complex Coeff Prime LFunction CoefficientField InCoefficientField coefficient_field LocalFactor LocalFactorData EulerProduct EulerProductData AnalyticDomain Normalization AnalyticContinuation FunctionalEquation NoConjecturalL2 HasseWeilSource HasseWeilLFunction AutomorphicSource AutomorphicLFunction HeckeCharacter HeckeLocalFactorNormalized HeckeEulerProductCompatible HeckeAutomorphicNormalization HeckeLFunction) => fun (cuspidal_representation_law : forall (pi : Family), CuspidalRepresentation pi -> AutomorphicRepresentation pi) => fun (automorphic_l_function_law : forall (pi : Family), AutomorphicRepresentation pi -> AutomorphicLFunction pi) => fun (rankin_selberg_product_law : forall (pi : Family), forall (sigma : Family), AutomorphicRepresentation pi -> AutomorphicRepresentation sigma -> RankinSelbergProduct pi sigma) => fun (rankin_selberg_analytic_law : forall (pi : Family), forall (sigma : Family), forall (s : Complex), RankinSelbergProduct pi sigma -> AutomorphicAnalyticAssumptions pi -> AutomorphicAnalyticAssumptions sigma -> RankinSelbergAnalyticSurface pi sigma s) => fun (langlands_shahidi_normalization_law : forall (pi : Family), AutomorphicRepresentation pi -> LanglandsShahidiNormalization pi) => fun (converse_theorem_law : forall (pi : Family), ConverseTheoremHypotheses pi -> AutomorphicRepresentation pi) => fun (trace_formula_map_law : forall (pi : Family), AutomorphicRepresentation pi -> TraceFormulaAssumptions pi -> TraceFormulaMap pi) => fun (analytic_continuation_l1_law : forall (pi : Family), AutomorphicRepresentation pi -> AutomorphicAnalyticAssumptions pi -> AnalyticContinuation pi (LFunction pi)) => fun (semistable_modularity_compatibility_law : forall (pi : Family), SemistableModularityCompatibility pi -> AutomorphicRepresentation pi) => rankin_selberg_analytic_law)"
    },
    {
      "declaration": "langlands_shahidi_normalization_surface",
      "source_kind": "explicit_term",
      "term": "fun Family => fun Complex => fun Coeff => fun Prime => fun LFunction => fun CoefficientField => fun InCoefficientField => fun coefficient_field => fun LocalFactor => fun LocalFactorData => fun EulerProduct => fun EulerProductData => fun AnalyticDomain => fun Normalization => fun AnalyticContinuation => fun FunctionalEquation => fun NoConjecturalL2 => fun HasseWeilSource => fun HasseWeilLFunction => fun AutomorphicSource => fun AutomorphicLFunction => fun HeckeCharacter => fun HeckeLocalFactorNormalized => fun HeckeEulerProductCompatible => fun HeckeAutomorphicNormalization => fun HeckeLFunction => fun AutomorphicRepresentation => fun CuspidalRepresentation => fun AutomorphicAnalyticAssumptions => fun RankinSelbergProduct => fun RankinSelbergAnalyticSurface => fun LanglandsShahidiNormalization => fun ConverseTheoremHypotheses => fun TraceFormulaAssumptions => fun TraceFormulaMap => fun SemistableModularityCompatibility => fun data => data (forall (pi : Family), AutomorphicRepresentation pi -> LanglandsShahidiNormalization pi) (fun (general_l_function_data : @LFunctionData Family Complex Coeff Prime LFunction CoefficientField InCoefficientField coefficient_field LocalFactor LocalFactorData EulerProduct EulerProductData AnalyticDomain Normalization AnalyticContinuation FunctionalEquation NoConjecturalL2 HasseWeilSource HasseWeilLFunction AutomorphicSource AutomorphicLFunction) => fun (hecke_l_data : @HeckeLData Family Complex Coeff Prime LFunction CoefficientField InCoefficientField coefficient_field LocalFactor LocalFactorData EulerProduct EulerProductData AnalyticDomain Normalization AnalyticContinuation FunctionalEquation NoConjecturalL2 HasseWeilSource HasseWeilLFunction AutomorphicSource AutomorphicLFunction HeckeCharacter HeckeLocalFactorNormalized HeckeEulerProductCompatible HeckeAutomorphicNormalization HeckeLFunction) => fun (cuspidal_representation_law : forall (pi : Family), CuspidalRepresentation pi -> AutomorphicRepresentation pi) => fun (automorphic_l_function_law : forall (pi : Family), AutomorphicRepresentation pi -> AutomorphicLFunction pi) => fun (rankin_selberg_product_law : forall (pi : Family), forall (sigma : Family), AutomorphicRepresentation pi -> AutomorphicRepresentation sigma -> RankinSelbergProduct pi sigma) => fun (rankin_selberg_analytic_law : forall (pi : Family), forall (sigma : Family), forall (s : Complex), RankinSelbergProduct pi sigma -> AutomorphicAnalyticAssumptions pi -> AutomorphicAnalyticAssumptions sigma -> RankinSelbergAnalyticSurface pi sigma s) => fun (langlands_shahidi_normalization_law : forall (pi : Family), AutomorphicRepresentation pi -> LanglandsShahidiNormalization pi) => fun (converse_theorem_law : forall (pi : Family), ConverseTheoremHypotheses pi -> AutomorphicRepresentation pi) => fun (trace_formula_map_law : forall (pi : Family), AutomorphicRepresentation pi -> TraceFormulaAssumptions pi -> TraceFormulaMap pi) => fun (analytic_continuation_l1_law : forall (pi : Family), AutomorphicRepresentation pi -> AutomorphicAnalyticAssumptions pi -> AnalyticContinuation pi (LFunction pi)) => fun (semistable_modularity_compatibility_law : forall (pi : Family), SemistableModularityCompatibility pi -> AutomorphicRepresentation pi) => langlands_shahidi_normalization_law)"
    },
    {
      "declaration": "converse_theorem_surface",
      "source_kind": "explicit_term",
      "term": "fun Family => fun Complex => fun Coeff => fun Prime => fun LFunction => fun CoefficientField => fun InCoefficientField => fun coefficient_field => fun LocalFactor => fun LocalFactorData => fun EulerProduct => fun EulerProductData => fun AnalyticDomain => fun Normalization => fun AnalyticContinuation => fun FunctionalEquation => fun NoConjecturalL2 => fun HasseWeilSource => fun HasseWeilLFunction => fun AutomorphicSource => fun AutomorphicLFunction => fun HeckeCharacter => fun HeckeLocalFactorNormalized => fun HeckeEulerProductCompatible => fun HeckeAutomorphicNormalization => fun HeckeLFunction => fun AutomorphicRepresentation => fun CuspidalRepresentation => fun AutomorphicAnalyticAssumptions => fun RankinSelbergProduct => fun RankinSelbergAnalyticSurface => fun LanglandsShahidiNormalization => fun ConverseTheoremHypotheses => fun TraceFormulaAssumptions => fun TraceFormulaMap => fun SemistableModularityCompatibility => fun data => data (forall (pi : Family), ConverseTheoremHypotheses pi -> AutomorphicRepresentation pi) (fun (general_l_function_data : @LFunctionData Family Complex Coeff Prime LFunction CoefficientField InCoefficientField coefficient_field LocalFactor LocalFactorData EulerProduct EulerProductData AnalyticDomain Normalization AnalyticContinuation FunctionalEquation NoConjecturalL2 HasseWeilSource HasseWeilLFunction AutomorphicSource AutomorphicLFunction) => fun (hecke_l_data : @HeckeLData Family Complex Coeff Prime LFunction CoefficientField InCoefficientField coefficient_field LocalFactor LocalFactorData EulerProduct EulerProductData AnalyticDomain Normalization AnalyticContinuation FunctionalEquation NoConjecturalL2 HasseWeilSource HasseWeilLFunction AutomorphicSource AutomorphicLFunction HeckeCharacter HeckeLocalFactorNormalized HeckeEulerProductCompatible HeckeAutomorphicNormalization HeckeLFunction) => fun (cuspidal_representation_law : forall (pi : Family), CuspidalRepresentation pi -> AutomorphicRepresentation pi) => fun (automorphic_l_function_law : forall (pi : Family), AutomorphicRepresentation pi -> AutomorphicLFunction pi) => fun (rankin_selberg_product_law : forall (pi : Family), forall (sigma : Family), AutomorphicRepresentation pi -> AutomorphicRepresentation sigma -> RankinSelbergProduct pi sigma) => fun (rankin_selberg_analytic_law : forall (pi : Family), forall (sigma : Family), forall (s : Complex), RankinSelbergProduct pi sigma -> AutomorphicAnalyticAssumptions pi -> AutomorphicAnalyticAssumptions sigma -> RankinSelbergAnalyticSurface pi sigma s) => fun (langlands_shahidi_normalization_law : forall (pi : Family), AutomorphicRepresentation pi -> LanglandsShahidiNormalization pi) => fun (converse_theorem_law : forall (pi : Family), ConverseTheoremHypotheses pi -> AutomorphicRepresentation pi) => fun (trace_formula_map_law : forall (pi : Family), AutomorphicRepresentation pi -> TraceFormulaAssumptions pi -> TraceFormulaMap pi) => fun (analytic_continuation_l1_law : forall (pi : Family), AutomorphicRepresentation pi -> AutomorphicAnalyticAssumptions pi -> AnalyticContinuation pi (LFunction pi)) => fun (semistable_modularity_compatibility_law : forall (pi : Family), SemistableModularityCompatibility pi -> AutomorphicRepresentation pi) => converse_theorem_law)"
    },
    {
      "declaration": "automorphic_l_trace_formula_prerequisites_map",
      "source_kind": "explicit_term",
      "term": "fun Family => fun Complex => fun Coeff => fun Prime => fun LFunction => fun CoefficientField => fun InCoefficientField => fun coefficient_field => fun LocalFactor => fun LocalFactorData => fun EulerProduct => fun EulerProductData => fun AnalyticDomain => fun Normalization => fun AnalyticContinuation => fun FunctionalEquation => fun NoConjecturalL2 => fun HasseWeilSource => fun HasseWeilLFunction => fun AutomorphicSource => fun AutomorphicLFunction => fun HeckeCharacter => fun HeckeLocalFactorNormalized => fun HeckeEulerProductCompatible => fun HeckeAutomorphicNormalization => fun HeckeLFunction => fun AutomorphicRepresentation => fun CuspidalRepresentation => fun AutomorphicAnalyticAssumptions => fun RankinSelbergProduct => fun RankinSelbergAnalyticSurface => fun LanglandsShahidiNormalization => fun ConverseTheoremHypotheses => fun TraceFormulaAssumptions => fun TraceFormulaMap => fun SemistableModularityCompatibility => fun data => data (forall (pi : Family), AutomorphicRepresentation pi -> TraceFormulaAssumptions pi -> TraceFormulaMap pi) (fun (general_l_function_data : @LFunctionData Family Complex Coeff Prime LFunction CoefficientField InCoefficientField coefficient_field LocalFactor LocalFactorData EulerProduct EulerProductData AnalyticDomain Normalization AnalyticContinuation FunctionalEquation NoConjecturalL2 HasseWeilSource HasseWeilLFunction AutomorphicSource AutomorphicLFunction) => fun (hecke_l_data : @HeckeLData Family Complex Coeff Prime LFunction CoefficientField InCoefficientField coefficient_field LocalFactor LocalFactorData EulerProduct EulerProductData AnalyticDomain Normalization AnalyticContinuation FunctionalEquation NoConjecturalL2 HasseWeilSource HasseWeilLFunction AutomorphicSource AutomorphicLFunction HeckeCharacter HeckeLocalFactorNormalized HeckeEulerProductCompatible HeckeAutomorphicNormalization HeckeLFunction) => fun (cuspidal_representation_law : forall (pi : Family), CuspidalRepresentation pi -> AutomorphicRepresentation pi) => fun (automorphic_l_function_law : forall (pi : Family), AutomorphicRepresentation pi -> AutomorphicLFunction pi) => fun (rankin_selberg_product_law : forall (pi : Family), forall (sigma : Family), AutomorphicRepresentation pi -> AutomorphicRepresentation sigma -> RankinSelbergProduct pi sigma) => fun (rankin_selberg_analytic_law : forall (pi : Family), forall (sigma : Family), forall (s : Complex), RankinSelbergProduct pi sigma -> AutomorphicAnalyticAssumptions pi -> AutomorphicAnalyticAssumptions sigma -> RankinSelbergAnalyticSurface pi sigma s) => fun (langlands_shahidi_normalization_law : forall (pi : Family), AutomorphicRepresentation pi -> LanglandsShahidiNormalization pi) => fun (converse_theorem_law : forall (pi : Family), ConverseTheoremHypotheses pi -> AutomorphicRepresentation pi) => fun (trace_formula_map_law : forall (pi : Family), AutomorphicRepresentation pi -> TraceFormulaAssumptions pi -> TraceFormulaMap pi) => fun (analytic_continuation_l1_law : forall (pi : Family), AutomorphicRepresentation pi -> AutomorphicAnalyticAssumptions pi -> AnalyticContinuation pi (LFunction pi)) => fun (semistable_modularity_compatibility_law : forall (pi : Family), SemistableModularityCompatibility pi -> AutomorphicRepresentation pi) => trace_formula_map_law)"
    },
    {
      "declaration": "automorphic_l_analytic_continuation_l1_boundary",
      "source_kind": "explicit_term",
      "term": "fun Family => fun Complex => fun Coeff => fun Prime => fun LFunction => fun CoefficientField => fun InCoefficientField => fun coefficient_field => fun LocalFactor => fun LocalFactorData => fun EulerProduct => fun EulerProductData => fun AnalyticDomain => fun Normalization => fun AnalyticContinuation => fun FunctionalEquation => fun NoConjecturalL2 => fun HasseWeilSource => fun HasseWeilLFunction => fun AutomorphicSource => fun AutomorphicLFunction => fun HeckeCharacter => fun HeckeLocalFactorNormalized => fun HeckeEulerProductCompatible => fun HeckeAutomorphicNormalization => fun HeckeLFunction => fun AutomorphicRepresentation => fun CuspidalRepresentation => fun AutomorphicAnalyticAssumptions => fun RankinSelbergProduct => fun RankinSelbergAnalyticSurface => fun LanglandsShahidiNormalization => fun ConverseTheoremHypotheses => fun TraceFormulaAssumptions => fun TraceFormulaMap => fun SemistableModularityCompatibility => fun data => data (forall (pi : Family), AutomorphicRepresentation pi -> AutomorphicAnalyticAssumptions pi -> AnalyticContinuation pi (LFunction pi)) (fun (general_l_function_data : @LFunctionData Family Complex Coeff Prime LFunction CoefficientField InCoefficientField coefficient_field LocalFactor LocalFactorData EulerProduct EulerProductData AnalyticDomain Normalization AnalyticContinuation FunctionalEquation NoConjecturalL2 HasseWeilSource HasseWeilLFunction AutomorphicSource AutomorphicLFunction) => fun (hecke_l_data : @HeckeLData Family Complex Coeff Prime LFunction CoefficientField InCoefficientField coefficient_field LocalFactor LocalFactorData EulerProduct EulerProductData AnalyticDomain Normalization AnalyticContinuation FunctionalEquation NoConjecturalL2 HasseWeilSource HasseWeilLFunction AutomorphicSource AutomorphicLFunction HeckeCharacter HeckeLocalFactorNormalized HeckeEulerProductCompatible HeckeAutomorphicNormalization HeckeLFunction) => fun (cuspidal_representation_law : forall (pi : Family), CuspidalRepresentation pi -> AutomorphicRepresentation pi) => fun (automorphic_l_function_law : forall (pi : Family), AutomorphicRepresentation pi -> AutomorphicLFunction pi) => fun (rankin_selberg_product_law : forall (pi : Family), forall (sigma : Family), AutomorphicRepresentation pi -> AutomorphicRepresentation sigma -> RankinSelbergProduct pi sigma) => fun (rankin_selberg_analytic_law : forall (pi : Family), forall (sigma : Family), forall (s : Complex), RankinSelbergProduct pi sigma -> AutomorphicAnalyticAssumptions pi -> AutomorphicAnalyticAssumptions sigma -> RankinSelbergAnalyticSurface pi sigma s) => fun (langlands_shahidi_normalization_law : forall (pi : Family), AutomorphicRepresentation pi -> LanglandsShahidiNormalization pi) => fun (converse_theorem_law : forall (pi : Family), ConverseTheoremHypotheses pi -> AutomorphicRepresentation pi) => fun (trace_formula_map_law : forall (pi : Family), AutomorphicRepresentation pi -> TraceFormulaAssumptions pi -> TraceFormulaMap pi) => fun (analytic_continuation_l1_law : forall (pi : Family), AutomorphicRepresentation pi -> AutomorphicAnalyticAssumptions pi -> AnalyticContinuation pi (LFunction pi)) => fun (semistable_modularity_compatibility_law : forall (pi : Family), SemistableModularityCompatibility pi -> AutomorphicRepresentation pi) => analytic_continuation_l1_law)"
    },
    {
      "declaration": "automorphic_l_semistable_modularity_compatibility_surface",
      "source_kind": "explicit_term",
      "term": "fun Family => fun Complex => fun Coeff => fun Prime => fun LFunction => fun CoefficientField => fun InCoefficientField => fun coefficient_field => fun LocalFactor => fun LocalFactorData => fun EulerProduct => fun EulerProductData => fun AnalyticDomain => fun Normalization => fun AnalyticContinuation => fun FunctionalEquation => fun NoConjecturalL2 => fun HasseWeilSource => fun HasseWeilLFunction => fun AutomorphicSource => fun AutomorphicLFunction => fun HeckeCharacter => fun HeckeLocalFactorNormalized => fun HeckeEulerProductCompatible => fun HeckeAutomorphicNormalization => fun HeckeLFunction => fun AutomorphicRepresentation => fun CuspidalRepresentation => fun AutomorphicAnalyticAssumptions => fun RankinSelbergProduct => fun RankinSelbergAnalyticSurface => fun LanglandsShahidiNormalization => fun ConverseTheoremHypotheses => fun TraceFormulaAssumptions => fun TraceFormulaMap => fun SemistableModularityCompatibility => fun data => data (forall (pi : Family), SemistableModularityCompatibility pi -> AutomorphicRepresentation pi) (fun (general_l_function_data : @LFunctionData Family Complex Coeff Prime LFunction CoefficientField InCoefficientField coefficient_field LocalFactor LocalFactorData EulerProduct EulerProductData AnalyticDomain Normalization AnalyticContinuation FunctionalEquation NoConjecturalL2 HasseWeilSource HasseWeilLFunction AutomorphicSource AutomorphicLFunction) => fun (hecke_l_data : @HeckeLData Family Complex Coeff Prime LFunction CoefficientField InCoefficientField coefficient_field LocalFactor LocalFactorData EulerProduct EulerProductData AnalyticDomain Normalization AnalyticContinuation FunctionalEquation NoConjecturalL2 HasseWeilSource HasseWeilLFunction AutomorphicSource AutomorphicLFunction HeckeCharacter HeckeLocalFactorNormalized HeckeEulerProductCompatible HeckeAutomorphicNormalization HeckeLFunction) => fun (cuspidal_representation_law : forall (pi : Family), CuspidalRepresentation pi -> AutomorphicRepresentation pi) => fun (automorphic_l_function_law : forall (pi : Family), AutomorphicRepresentation pi -> AutomorphicLFunction pi) => fun (rankin_selberg_product_law : forall (pi : Family), forall (sigma : Family), AutomorphicRepresentation pi -> AutomorphicRepresentation sigma -> RankinSelbergProduct pi sigma) => fun (rankin_selberg_analytic_law : forall (pi : Family), forall (sigma : Family), forall (s : Complex), RankinSelbergProduct pi sigma -> AutomorphicAnalyticAssumptions pi -> AutomorphicAnalyticAssumptions sigma -> RankinSelbergAnalyticSurface pi sigma s) => fun (langlands_shahidi_normalization_law : forall (pi : Family), AutomorphicRepresentation pi -> LanglandsShahidiNormalization pi) => fun (converse_theorem_law : forall (pi : Family), ConverseTheoremHypotheses pi -> AutomorphicRepresentation pi) => fun (trace_formula_map_law : forall (pi : Family), AutomorphicRepresentation pi -> TraceFormulaAssumptions pi -> TraceFormulaMap pi) => fun (analytic_continuation_l1_law : forall (pi : Family), AutomorphicRepresentation pi -> AutomorphicAnalyticAssumptions pi -> AnalyticContinuation pi (LFunction pi)) => fun (semistable_modularity_compatibility_law : forall (pi : Family), SemistableModularityCompatibility pi -> AutomorphicRepresentation pi) => semistable_modularity_compatibility_law)"
    }
  ],
  "acceptance": {
    "required": ["decode_module_cert", "verify_module_cert"],
    "accepted_artifact": "Proofs/Ai/NumberTheory/AutomorphicL/certificate.npcert"
  }
}
